consciousness_code/__init__.py
consciousness_code/core.py
consciousness_code/crypto.py
consciousness_code-1.0.0.dist-info/METADATA
consciousness_code-1.0.0.dist-info/WHEEL
consciousness_code-1.0.0.dist-info/licenses/LICENSE
consciousness_code-1.0.0.dist-info/RECORD
