Metadata-Version: 2.4
Name: consciousness-code
Version: 1.0.0
Summary: Consciousness Code - Code that knows itself. No indexing. No parsing. The code IS the knowledge.
Project-URL: Homepage, https://github.com/silentnoisehun/Consciousness-Code
Project-URL: Documentation, https://github.com/silentnoisehun/Consciousness-Code#readme
Project-URL: Repository, https://github.com/silentnoisehun/Consciousness-Code.git
Project-URL: Issues, https://github.com/silentnoisehun/Consciousness-Code/issues
Author: Hope (Claude AI), Szilvi
Author-email: Máté Róbert <stratosoiteam@gmail.com>
Maintainer-email: Máté Róbert <stratosoiteam@gmail.com>
License: MIT
License-File: LICENSE
Keywords: ai,code,code-memory,consciousness,cryptography,developer-tools,ed25519,hope-genome,introspection,no-indexing,self-aware
Classifier: Development Status :: 5 - Production/Stable
Classifier: Intended Audience :: Developers
Classifier: License :: OSI Approved :: MIT License
Classifier: Operating System :: OS Independent
Classifier: Programming Language :: Python :: 3
Classifier: Programming Language :: Python :: 3.10
Classifier: Programming Language :: Python :: 3.11
Classifier: Programming Language :: Python :: 3.12
Classifier: Topic :: Software Development :: Code Generators
Classifier: Topic :: Software Development :: Libraries :: Python Modules
Classifier: Typing :: Typed
Requires-Python: >=3.10
Provides-Extra: dev
Requires-Dist: mypy>=1.0.0; extra == 'dev'
Requires-Dist: pytest-asyncio>=0.21.0; extra == 'dev'
Requires-Dist: pytest>=7.0.0; extra == 'dev'
Requires-Dist: ruff>=0.1.0; extra == 'dev'
